[
  {
    "bookname": "Isaiah",
    "chapter": "46",
    "text": "<p class=\"poetry\"><st data-num=\"01078\" class=\"\">Bel</st><n id=\"1\" /> <st data-num=\"03766\" class=\"\">kneels down</st>,<p class=\"poetry\"><st data-num=\"05015\" class=\"\">Nebo</st><n id=\"2\" /> <st data-num=\"07164\" class=\"\">bends low</st>. <p class=\"poetry\">Their <st data-num=\"06091\" class=\"\">images</st> <st data-num=\"01961\">weigh down</st> <st data-num=\"02416\" class=\"\">animals</st> and <st data-num=\"0929\" class=\"\">beasts</st>.<n id=\"3\" /> <p class=\"poetry\">Your <st data-num=\"06006\" class=\"\">heavy</st> <st data-num=\"05385\" class=\"\">images</st> are <st data-num=\"04853\" class=\"\">burdensome</st> to <st data-num=\"05889\" class=\"\">tired</st> animals.<n id=\"4\" /> </p>",
    "verse": "1"
  },
  {
    "bookname": "Isaiah",
    "chapter": "46",
    "text": "<p class=\"poetry\"><st data-num=\"03162\" class=\"\">Together</st> they <st data-num=\"07164\" class=\"\">bend low</st> and <st data-num=\"03766\" class=\"\">kneel down</st>;<p class=\"poetry\">they are <st data-num=\"03808 03201\">unable</st> to <st data-num=\"04422\" class=\"\">rescue</st> the <st data-num=\"04853\" class=\"\">images</st>;<n id=\"1\" /> <p class=\"poetry\">they <st data-num=\"05315\" class=\"\">themselves</st><n id=\"2\" /> <st data-num=\"01980\" class=\"\">head off</st> into <st data-num=\"07628\" class=\"\">captivity</st>.<n id=\"3\" /> </p>",
    "verse": "2"
  },
  {
    "bookname": "Isaiah",
    "chapter": "46",
    "text": "<p class=\"poetry\">\u201c<st data-num=\"08085\" class=\"\">Listen</st> <st data-num=\"0413\" class=\"\">to</st> me, O <st data-num=\"01004\" class=\"\">family</st> of <st data-num=\"03290\" class=\"\">Jacob</st>,<n id=\"1\" /> <p class=\"poetry\"><st data-num=\"03605\" class=\"\">all</st> you <st data-num=\"07611\" class=\"\">who are left</st> from the <st data-num=\"01004\" class=\"\">family</st> of <st data-num=\"03478\" class=\"\">Israel</st>,<n id=\"2\" /> <p class=\"poetry\">you who have been <st data-num=\"06006\" class=\"\">carried</st> <st data-num=\"04480\" class=\"\">from</st> <st data-num=\"0990\" class=\"\">birth</st>,<n id=\"3\" /> <p class=\"poetry\">you who have been <st data-num=\"05375\" class=\"\">supported</st> <st data-num=\"04480\" class=\"\">from</st> the time you left the <st data-num=\"07356\" class=\"\">womb</st>.<n id=\"4\" /> </p>",
    "verse": "3"
  },
  {
    "bookname": "Isaiah",
    "chapter": "46",
    "text": "<p class=\"poetry\"><st data-num=\"05704\" class=\"\">Even</st> when you are <st data-num=\"02209\" class=\"\">old</st>, <st data-num=\"0589\" class=\"\">I</st> will <st data-num=\"01931\" class=\"\">take care</st> of you,<n id=\"1\" /> <p class=\"poetry\"><st data-num=\"05704\" class=\"\">even</st> when you have <st data-num=\"07872\" class=\"\">gray hair</st>, <st data-num=\"0589\" class=\"\">I</st> will <st data-num=\"05445\" class=\"\">carry</st> you.<p class=\"poetry\"><st data-num=\"0589\" class=\"\">I</st> <st data-num=\"06213\" class=\"\">made</st> you and <st data-num=\"0589\" class=\"\">I</st> will <st data-num=\"05375\" class=\"\">support</st> you;<p class=\"poetry\"><st data-num=\"0589\" class=\"\">I</st> will <st data-num=\"05445\" class=\"\">carry</st> you and <st data-num=\"04422\" class=\"\">rescue</st> you.<n id=\"2\" /></p>",
    "verse": "4"
  },
  {
    "bookname": "Isaiah",
    "chapter": "46",
    "text": "<p class=\"poetry\">To <st data-num=\"04310\" class=\"\">whom</st> can you <st data-num=\"01819\" class=\"\">compare</st> and <st data-num=\"07737\" class=\"\">liken</st> me?<p class=\"poetry\">Tell me whom you think I <st data-num=\"04911\" class=\"\">resemble</st>, so we can be <st data-num=\"01819\" class=\"\">compared</st>! </p>",
    "verse": "5"
  },
  {
    "bookname": "Isaiah",
    "chapter": "46",
    "text": "<p class=\"poetry\">Those who <st data-num=\"02107\" class=\"\">empty out</st> <st data-num=\"02091\" class=\"\">gold</st> from a <st data-num=\"03599\" class=\"\">purse</st><p class=\"poetry\">and <st data-num=\"08254\" class=\"\">weigh out</st> <st data-num=\"03701\" class=\"\">silver</st> on the <st data-num=\"07070\" class=\"\">scale</st><n id=\"1\" /> <p class=\"poetry\"><st data-num=\"07936\" class=\"\">hire</st> a <st data-num=\"06884\" class=\"\">metalsmith</st>, who <st data-num=\"06213\" class=\"\">makes</st> it into a <st data-num=\"0410\" class=\"\">god</st>.<p class=\"poetry\">They then <st data-num=\"05456\" class=\"\">bow down</st> <st data-num=\"0637\" class=\"\">and</st> <st data-num=\"07812\" class=\"\">worship</st> it.</p>",
    "verse": "6"
  },
  {
    "bookname": "Isaiah",
    "chapter": "46",
    "text": "<p class=\"poetry\">They <st data-num=\"05375\" class=\"\">put</st> it <st data-num=\"05921\" class=\"\">on</st> their <st data-num=\"03802\" class=\"\">shoulder</st> and <st data-num=\"05445\" class=\"\">carry</st> it;<p class=\"poetry\">they <st data-num=\"03240\" class=\"\">put</st> it <st data-num=\"08478\" class=\"\">in</st> its <st data-num=\"08478\" class=\"\">place</st> and it just <st data-num=\"05975\" class=\"\">stands</st> there;<p class=\"poetry\">it does <st data-num=\"03808\" class=\"\">not</st><n id=\"1\" /> <st data-num=\"04185\" class=\"\">move</st> from its <st data-num=\"04725\" class=\"\">place</st>.<p class=\"poetry\"><st data-num=\"0637\" class=\"\">Even</st> when someone <st data-num=\"06817\" class=\"\">cries out</st> <st data-num=\"0413\" class=\"\">to</st> it, it does <st data-num=\"03808\" class=\"\">not</st> <st data-num=\"06030\" class=\"\">reply</st>;<p class=\"poetry\">it does <st data-num=\"03808\" class=\"\">not</st> <st data-num=\"03467\" class=\"\">deliver</st> him from his <st data-num=\"06869\" class=\"\">distress</st>. </p>",
    "verse": "7"
  },
  {
    "bookname": "Isaiah",
    "chapter": "46",
    "text": "<p class=\"poetry\"><st data-num=\"02142\" class=\"\">Remember</st> <st data-num=\"02063\" class=\"\">this</st>, so you can <st data-num=\"0377\" class=\"\">be brave</st>.<n id=\"1\" /> <p class=\"poetry\"><st data-num=\"07725\" class=\"\">Think</st> <st data-num=\"05921\" class=\"\">about</st> <st data-num=\"03820\" class=\"\">it</st>, you <st data-num=\"06586\" class=\"\">rebels</st>!<n id=\"2\" /></p>",
    "verse": "8"
  },
  {
    "bookname": "Isaiah",
    "chapter": "46",
    "text": "<p class=\"poetry\"><st data-num=\"02142\" class=\"\">Remember</st> <st data-num=\"07223\" class=\"\">what</st> I <st data-num=\"07223\" class=\"\">accomplished</st> in <st data-num=\"05769\" class=\"\">antiquity</st>.<n id=\"1\" /> <p class=\"poetry\"><st data-num=\"03588\" class=\"\">Truly</st> <st data-num=\"0595\" class=\"\">I</st> am <st data-num=\"0410\" class=\"\">God</st>, I have <st data-num=\"0369\" class=\"\">no</st> <st data-num=\"05750\" class=\"\">peer</st>;<n id=\"2\" /> <p class=\"poetry\">I am <st data-num=\"0430\" class=\"\">God</st>, and there is <st data-num=\"0657\" class=\"\">none</st> <st data-num=\"03644\" class=\"\">like</st> me,</p>",
    "verse": "9"
  },
  {
    "bookname": "Isaiah",
    "chapter": "46",
    "text": "<p class=\"poetry\">who <st data-num=\"05046\" class=\"\">announces</st> the <st data-num=\"0319\" class=\"\">end</st> from the <st data-num=\"07225\" class=\"\">beginning</st><p class=\"poetry\">and reveals <st data-num=\"06924\" class=\"\">beforehand</st><n id=\"1\" /> <st data-num=\"0834\" class=\"\">what</st> has <st data-num=\"03808\" class=\"\">not</st> yet <st data-num=\"06213\" class=\"\">occurred</st>;<p class=\"poetry\">who <st data-num=\"0559\" class=\"\">says</st>, \u2018My <st data-num=\"06098\" class=\"\">plan</st> will <st data-num=\"06965\" class=\"\">be realized</st>,<p class=\"poetry\">I will <st data-num=\"06213\" class=\"\">accomplish</st> <st data-num=\"03605\" class=\"\">what</st> I <st data-num=\"02656\" class=\"\">desire</st>;\u2019 </p>",
    "verse": "10"
  },
  {
    "bookname": "Isaiah",
    "chapter": "46",
    "text": "<p class=\"poetry\">who <st data-num=\"07121\" class=\"\">summons</st> an <st data-num=\"05861\" class=\"\">eagle</st><n id=\"1\" /> from the <st data-num=\"04217\" class=\"\">east</st>,<p class=\"poetry\">from a <st data-num=\"04801\" class=\"\">distant</st> <st data-num=\"0776\" class=\"\">land</st>, <st data-num=\"0376\" class=\"\">one</st> who carries out my <st data-num=\"06098\" class=\"\">plan</st>.<p class=\"poetry\"><st data-num=\"0637\" class=\"\">Yes</st>, I have <st data-num=\"01696\" class=\"\">decreed</st>,<n id=\"2\" /> <p class=\"poetry\"><st data-num=\"0637\" class=\"\">yes</st>, I will <st data-num=\"0935\" class=\"\">bring</st> it <st data-num=\"0935\" class=\"\">to pass</st>;<p class=\"poetry\">I have <st data-num=\"03335\" class=\"\">formulated a plan</st>,<p class=\"poetry\"><st data-num=\"0637\" class=\"\">yes</st>, I will <st data-num=\"06213\" class=\"\">carry</st> it <st data-num=\"06213\" class=\"\">out</st>. </p>",
    "verse": "11"
  },
  {
    "bookname": "Isaiah",
    "chapter": "46",
    "text": "<p class=\"poetry\"><st data-num=\"08085\" class=\"\">Listen</st> <st data-num=\"0413\" class=\"\">to</st> me, you <st data-num=\"047\" class=\"\">stubborn</st> <st data-num=\"03820\" class=\"\">people</st>,<n id=\"1\" /> <p class=\"poetry\">you who <st data-num=\"07350\" class=\"\">distance</st> yourselves from doing <st data-num=\"06666\" class=\"\">what is right</st>.<n id=\"2\" /> </p>",
    "verse": "12"
  },
  {
    "bookname": "Isaiah",
    "chapter": "46",
    "text": "<p class=\"poetry\">I am <st data-num=\"07126\" class=\"\">bringing</st> my <st data-num=\"06666\" class=\"\">deliverance</st> <st data-num=\"07126\" class=\"\">near</st>, it <st data-num=\"07368\" class=\"\">is</st> <st data-num=\"03808\" class=\"\">not</st> <st data-num=\"07368\" class=\"\">far away</st>;<p class=\"poetry\">I am bringing my <st data-num=\"08668\" class=\"\">salvation</st> near,<n id=\"1\" /> it does <st data-num=\"03808\" class=\"\">not</st> <st data-num=\"0309\" class=\"\">wait</st>.<p class=\"poetry\">I will <st data-num=\"05414 08668\">save</st> <st data-num=\"06726\" class=\"\">Zion</st>;<n id=\"2\" /> <p class=\"poetry\">I will <st data-num=\"08597\" class=\"\">adorn</st> <st data-num=\"03478\" class=\"\">Israel</st> <st data-num=\"08597\" class=\"\">with</st> my <st data-num=\"08597\" class=\"\">splendor</st>.<n id=\"3\" /> </p>",
    "verse": "13"
  }
]